[
  {
    "race_datetime": "26/08/2025 18:55",
    "course": "Bellewstown",
    "horse": "Aurora Nova",
    "bookie_odds": "13.00",
    "model_odds": 10.64,
    "raw_odds": "4.57",
    "tags": [
      "raw-value"
    ],
    "data_coverage": 100.0,
    "race_data_confidence": 98.61111111111111
  },
  {
    "race_datetime": "26/08/2025 19:25",
    "course": "Bellewstown",
    "horse": "Radar Ahead",
    "bookie_odds": "15.00",
    "model_odds": 12.16,
    "raw_odds": "3.78",
    "tags": [
      "blue",
      "raw-value"
    ],
    "data_coverage": 100.0,
    "race_data_confidence": 68.75
  },
  {
    "race_datetime": "26/08/2025 19:55",
    "course": "Bellewstown",
    "horse": "Curious Bride",
    "bookie_odds": "67.00",
    "model_odds": 52.89,
    "raw_odds": "10.67",
    "tags": [
      "blue",
      "raw-value"
    ],
    "data_coverage": 100.0,
    "race_data_confidence": 100.0
  }
]